{"flagWords":[],"words":["lezer","nvim","statusline","treesitter","autopairs","keymap","tailwindcss","neovim","daemonized","lspconfig","builtins","checkhealth","pnpm","augroup","bufnr","dotfiles","nullvoxpopuli","Passwordless","Yubikey","envfile","noninteractive","Ryzen","glimdown","instanceof","unidirectionally","codemirror","tabindex","fontawesome","fortawesome","runloop","iframe","Statecharts","xstate","qunit","htmlbars","statechart","concat","keydown","cosmiconfig","typecheck","transpiles","Entrypoints","turborepo","gsettings","browserslis","strictnesses","starships","typeof","noreferrer","noopener","penpal","preconfigured","Kenobi","Kenobi","testem","iframes","yarg","Solorepo","Listr","execa","Unplugin","rehype","curlies","stackblitz","camelcase","commiting","highlightjs","Parallelizable","backburner","javascripts","Uncategorized","dasherized","deno","frum","vimium","popperjs","HTMLI","Tatooine","Hoth","quickstart","embereños","Colocated","browserstack","SIGINT","preprocess","colocation","starbeam","accum","invocables","Styleguide","klass","callout","falsey","devs","destroyables","Autotracking","codemods","headlessui","lockfiles","prember","Fastboot","inflector","mktmp","mktmp","Codeowners","codeowner","fixturify"],"version":"0.2","language":"en","ignorePaths":["node_modules\/**","dist\/**",".git\/**","tmp\/**","declarations\/**"]}
